cli.py
engine.py
core/__init__.py
core/config.py
core/context_integration.py
core/dynamic_cli.py
core/registry.py
core/scenario_loader.py
core/scenario_registry.py
core/template_generator.py
core/template_helpers.py
core/tutorials.py
nodecraft-0.2.2.data/data/prompts/arch_drift.prompt.md
nodecraft-0.2.2.data/data/prompts/rag_query.prompt.md
nodecraft-0.2.2.data/data/prompts/regression.prompt.md
nodecraft-0.2.2.data/data/prompts/repo_adapt.prompt.md
nodecraft-0.2.2.data/data/prompts/snapshot.prompt.md
nodes/__init__.py
nodes/common/__init__.py
nodes/common/call_llm_node.py
nodes/common/fetch_files.py
nodes/common/fetch_files_node.py
nodes/common/files_to_prompt_node.py
nodes/common/get_files_node.py
nodes/common/parse_code_node.py
nodes/common/save_snapshot_node.py
nodes/common/snapshot_files_node.py
nodes/common/write_file_node.py
nodes/common/diff/__init__.py
nodes/common/diff/get_git_diff_node.py
nodes/common/diff/parse_diff_node.py
nodes/common/review/__init__.py
nodes/common/review/aggregate_findings_node.py
nodes/common/review/performance_review_node.py
nodes/common/review/quality_review_node.py
nodes/common/review/security_review_node.py
nodes/custom/__init__.py
nodes/custom/check_naming_convention_node.py
nodes/tutorial/__init__.py
nodes/tutorial/tutorial_nodes.py
nodes/tutorial/tutorial_nodes_temp.py
prompts/__init__.py
prompts/arch_drift.prompt.md
prompts/rag_query.prompt.md
prompts/regression.prompt.md
prompts/repo_adapt.prompt.md
prompts/snapshot.prompt.md
scenarios/__init__.py
scenarios/scenario_1_local_snapshot.py
scenarios/scenario_2_repo_adapt.py
scenarios/scenario_3_regression.py
scenarios/scenario_4_arch_drift.py
scenarios/scenario_5_local_rag.py
scenarios/scenario_6_code_review.py
scenarios/scenario_7_codebase_tutorial.py
scenarios/templates/code_analysis.yaml
scenarios/templates/file_collector.yaml
scenarios/templates/simple_rag.yaml
utils/__init__.py
utils/ast_parser.py
utils/crawl_github_files.py
utils/crawl_local_files.py
utils/llm_client.py
nodecraft-0.2.2.dist-info/METADATA
nodecraft-0.2.2.dist-info/WHEEL
nodecraft-0.2.2.dist-info/entry_points.txt
nodecraft-0.2.2.dist-info/top_level.txt
nodecraft-0.2.2.dist-info/RECORD
